django_ping_me/__init__.py
django_ping_me/admin.py
django_ping_me/apps.py
django_ping_me/cron.py
django_ping_me/migrations/0001_initial.py
django_ping_me/migrations/__init__.py
django_ping_me/models.py
django_ping_me/templates/ping_me/domain_list.html
django_ping_me/templates/ping_me/partials/delete_form.html
django_ping_me/templates/ping_me/partials/delete_popup.html
django_ping_me/templates/ping_me/partials/edit_form.html
django_ping_me/templates/ping_me/partials/edit_popup.html
django_ping_me/templates/ping_me/partials/summary_percentage.html
django_ping_me/tests.py
django_ping_me/urls.py
django_ping_me/views.py
django_ping_me-0.1.0.dist-info/LICENSE
django_ping_me-0.1.0.dist-info/WHEEL
django_ping_me-0.1.0.dist-info/METADATA
django_ping_me-0.1.0.dist-info/RECORD
