Metadata-Version: 2.1
Name: django-ping-me
Version: 0.1.0
Summary: Django application to create availability statistics of web servers
Home-page: https://gitlab.com/aloha68/django-ping-me
License: ISC
Keywords: django
Author: Aloha68
Author-email: dev@aloha.im
Requires-Python: >=3.5,<4.0
Classifier: Environment :: Web Environment
Classifier: Framework :: Django
Classifier: Framework :: Django :: 2.0
Classifier: License :: OSI Approved
Classifier: Operating System :: OS Independent
Classifier: Programming Language :: Python :: 3
Classifier: Programming Language :: Python :: 3.5
Classifier: Programming Language :: Python :: 3.6
Classifier: Programming Language :: Python :: 3.7
Classifier: Topic :: Communications
Requires-Dist: django (>=2.2,<3.0)
Requires-Dist: django-cron (==0.5.1)
Requires-Dist: libaloha (>=0,<1)
Requires-Dist: markdown (>=2.6,<3.0)
Project-URL: Repository, https://gitlab.com/aloha68/django-ping-me
